mirageml/__init__.py
mirageml/__main__.py
mirageml/constants.py
mirageml/commands/__init__.py
mirageml/commands/add_model.py
mirageml/commands/add_source.py
mirageml/commands/add_system_prompt.py
mirageml/commands/chat.py
mirageml/commands/config.py
mirageml/commands/delete_source.py
mirageml/commands/delete_system_prompt.py
mirageml/commands/list_models.py
mirageml/commands/list_sources.py
mirageml/commands/list_system_prompts.py
mirageml/commands/login.py
mirageml/commands/profile.py
mirageml/commands/rag.py
mirageml/commands/tutorial.py
mirageml/commands/utils/__init__.py
mirageml/commands/utils/codeblocks.py
mirageml/commands/utils/custom_inputs.py
mirageml/commands/utils/llm.py
mirageml/commands/utils/local_source.py
mirageml/commands/utils/prompt_templates.py
mirageml/commands/utils/type_check.py
mirageml/commands/utils/vectordb.py
mirageml/commands/utils/web_source.py
mirageml_version/__init__.py
mirageml_version/_version_generated.py
mirageml-1.1.6.dist-info/METADATA
mirageml-1.1.6.dist-info/WHEEL
mirageml-1.1.6.dist-info/dependency_links.txt
mirageml-1.1.6.dist-info/entry_points.txt
mirageml-1.1.6.dist-info/top_level.txt
mirageml-1.1.6.dist-info/RECORD
