Metadata-Version: 2.1
Name: mirageml
Version: 1.1.6
Summary: Your Personal AGI
Author: Mirage ML Inc
Author-email: support@mirageml.com
Requires-Dist: rich ==13.5.2
Requires-Dist: typer ==0.9.0
Requires-Dist: chardet ==5.2.0
Requires-Dist: qdrant-client ==1.6.0
Requires-Dist: ctransformers ==0.2.27
Requires-Dist: pyjwt ==2.8.0
Requires-Dist: keyring ==24.2.0
Requires-Dist: requests ==2.31.0
Requires-Dist: supabase ==1.2.0
Requires-Dist: segment-analytics-python ==2.2.3
Requires-Dist: pyperclip ==1.8.2
Requires-Dist: prompt-toolkit ==3.0.39
Requires-Dist: tiktoken ==0.5.1
Requires-Dist: langchain ==0.0.279
Requires-Dist: typing-extensions ==4.8.0
Requires-Dist: cffi ==1.16.0
Requires-Dist: pathspec ==0.11.2
Requires-Dist: fastembed
